xpring/__init__.py
xpring/algorithms/__init__.py
xpring/algorithms/__init__.pyi
xpring/algorithms/ed25519.py
xpring/algorithms/secp256k1.py
xpring/algorithms/signing.py
xpring/bits.py
xpring/client.py
xpring/codec.py
xpring/definitions.json
xpring/hashes.py
xpring/key_pair.py
xpring/proto/__init__.py
xpring/proto/v1/__init__.py
xpring/proto/v1/account_pb2.py
xpring/proto/v1/account_pb2.pyi
xpring/proto/v1/account_pb2_grpc.py
xpring/proto/v1/amount_pb2.py
xpring/proto/v1/amount_pb2.pyi
xpring/proto/v1/amount_pb2_grpc.py
xpring/proto/v1/common_pb2.py
xpring/proto/v1/common_pb2.pyi
xpring/proto/v1/common_pb2_grpc.py
xpring/proto/v1/get_account_info_pb2.py
xpring/proto/v1/get_account_info_pb2.pyi
xpring/proto/v1/get_account_info_pb2_grpc.py
xpring/proto/v1/get_account_transaction_history_pb2.py
xpring/proto/v1/get_account_transaction_history_pb2.pyi
xpring/proto/v1/get_account_transaction_history_pb2_grpc.py
xpring/proto/v1/get_fee_pb2.py
xpring/proto/v1/get_fee_pb2.pyi
xpring/proto/v1/get_fee_pb2_grpc.py
xpring/proto/v1/get_ledger_data_pb2.py
xpring/proto/v1/get_ledger_data_pb2.pyi
xpring/proto/v1/get_ledger_data_pb2_grpc.py
xpring/proto/v1/get_ledger_diff_pb2.py
xpring/proto/v1/get_ledger_diff_pb2.pyi
xpring/proto/v1/get_ledger_diff_pb2_grpc.py
xpring/proto/v1/get_ledger_entry_pb2.py
xpring/proto/v1/get_ledger_entry_pb2.pyi
xpring/proto/v1/get_ledger_entry_pb2_grpc.py
xpring/proto/v1/get_ledger_pb2.py
xpring/proto/v1/get_ledger_pb2.pyi
xpring/proto/v1/get_ledger_pb2_grpc.py
xpring/proto/v1/get_transaction_pb2.py
xpring/proto/v1/get_transaction_pb2.pyi
xpring/proto/v1/get_transaction_pb2_grpc.py
xpring/proto/v1/ledger_objects_pb2.py
xpring/proto/v1/ledger_objects_pb2.pyi
xpring/proto/v1/ledger_objects_pb2_grpc.py
xpring/proto/v1/ledger_pb2.py
xpring/proto/v1/ledger_pb2.pyi
xpring/proto/v1/ledger_pb2_grpc.py
xpring/proto/v1/meta_pb2.py
xpring/proto/v1/meta_pb2.pyi
xpring/proto/v1/meta_pb2_grpc.py
xpring/proto/v1/submit_pb2.py
xpring/proto/v1/submit_pb2.pyi
xpring-0.6.3.dist-info/LICENSE
xpring-0.6.3.dist-info/WHEEL
xpring-0.6.3.dist-info/METADATA
xpring-0.6.3.dist-info/RECORD
