Metadata-Version: 2.1
Name: xpring
Version: 0.6.3
Summary: 
Home-page: https://github.com/thejohnfreeman/xpring-py/
License: ISC
Author: John Freeman
Author-email: jfreeman@ripple.com
Requires-Python: >=3.6
Classifier: License :: OSI Approved
Classifier: Programming Language :: Python :: 3
Classifier: Programming Language :: Python :: 3.10
Classifier: Programming Language :: Python :: 3.6
Classifier: Programming Language :: Python :: 3.7
Classifier: Programming Language :: Python :: 3.8
Classifier: Programming Language :: Python :: 3.9
Provides-Extra: docs
Provides-Extra: py
Requires-Dist: dataclasses (>=0.6.0,<0.7.0)
Requires-Dist: ecdsa (>=0.15.0,<0.16.0)
Requires-Dist: fastecdsa (>=2.1.1,<3.0.0); extra == "py"
Requires-Dist: grpcio (>=1.24,<2.0)
Requires-Dist: protobuf (>=3.0,<4.0)
Requires-Dist: pynacl (>=1.3,<2.0)
Requires-Dist: sphinx (>=1.8,<2.0); extra == "docs"
Requires-Dist: sphinx-autobuild (>=0.7.1,<0.8.0); extra == "docs"
Requires-Dist: sphinx_rtd_theme (>=0.4.3,<0.5.0); extra == "docs"
Requires-Dist: toml (>=0.10.0,<0.11.0); extra == "docs"
Requires-Dist: typing_extensions (>=3.7,<4.0)
Project-URL: Documentation, https://xpring-py.readthedocs.io/
Project-URL: Repository, https://github.com/thejohnfreeman/xpring-py/
